cmsplugin_pygments/__init__.py
cmsplugin_pygments/cms_plugins.py
cmsplugin_pygments/models.py
cmsplugin_pygments/migrations/0001_initial.py
cmsplugin_pygments/migrations/0002_auto_20180223_1743.py
cmsplugin_pygments/migrations/__init__.py
cmsplugin_pygments/templates/cmsplugin_pygments/pygments.html
cmsplugin_pygments-0.8.3.dist-info/DESCRIPTION.rst
cmsplugin_pygments-0.8.3.dist-info/METADATA
cmsplugin_pygments-0.8.3.dist-info/RECORD
cmsplugin_pygments-0.8.3.dist-info/WHEEL
cmsplugin_pygments-0.8.3.dist-info/metadata.json
cmsplugin_pygments-0.8.3.dist-info/top_level.txt
