Metadata-Version: 2.0
Name: cmsplugin-pygments
Version: 0.8.3
Summary: django-cms plugin for pygments
Home-page: https://github.com/jedie/cmsplugin-pygments
Author: Jens Diemer
Author-email: cmsplugin-pygments@jensdiemer.de
License: BSD
Platform: UNKNOWN
Classifier: Development Status :: 4 - Beta
Classifier: Framework :: Django
Classifier: Intended Audience :: Developers
Classifier: License :: OSI Approved :: BSD License
Classifier: Operating System :: OS Independent
Classifier: Programming Language :: Python
Classifier: Programming Language :: Python :: 2.7
Classifier: Programming Language :: Python :: 3.4
Classifier: Programming Language :: Python :: 3.5
Classifier: Framework :: Django
Classifier: Topic :: Internet :: WWW/HTTP
Requires-Dist: pygments
